env_validate/__init__.py
env_validate/env_validate.py
env_validate-0.4.dist-info/LICENSE
env_validate-0.4.dist-info/METADATA
env_validate-0.4.dist-info/WHEEL
env_validate-0.4.dist-info/top_level.txt
env_validate-0.4.dist-info/RECORD
