Metadata-Version: 2.1
Name: env-validate
Version: 0.4
Summary: UNKNOWN
Home-page: https://github.com/chrisjsimpson/env-validate
Author: Karma Computing
Author-email: oss@karmacomputing.co.uk
License: UNKNOWN
Platform: UNKNOWN
Classifier: Programming Language :: Python :: 3
Classifier: License :: OSI Approved :: GNU Affero General Public License v3
Classifier: Operating System :: OS Independent
Requires-Python: >=3
License-File: LICENSE
